gambas/__init__.py
gambas/command.py
gambas/factory.py
gambas/manager.py
gambas/run.py
gambas/validator.py
gambas/tests/__init__.py
gambas/tests/conftest.py
gambas/tests/test_command.py
gambas/tests/test_manager.py
gambas/tests/test_validator.py
gambas-0.0.3.dist-info/LICENSE
gambas-0.0.3.dist-info/METADATA
gambas-0.0.3.dist-info/WHEEL
gambas-0.0.3.dist-info/entry_points.txt
gambas-0.0.3.dist-info/top_level.txt
gambas-0.0.3.dist-info/RECORD
