Metadata-Version: 2.1
Name: gambas
Version: 0.0.3
Summary: Config Key Validator
Home-page: https://github.com/linewalks/gambas
Author: Linewalks
Author-email: yy.chung@linewalks.com
License: UNKNOWN
Platform: UNKNOWN
Classifier: License :: OSI Approved :: MIT License
Requires-Python: >= 3.6
License-File: LICENSE
